{
  "@type": "Models.Scardyshroom",
  "@val": {
    "pea": {
      "effect": {
        "slowDuration": 0,
        "stunDuration": 0,
        "slow": false,
        "stun": false
      },
      "damagePerShoot": 1,
      "pierce": false
    },
    "numberOfBulletsPerShoot": 1,
    "coolDownForNextShoot": 2,
    "currentCoolDownForNextShoot": 0,
    "direction": "Right",
    "requiredSuns": 1,
    "coolDownTime": 2,
    "currentCoolDownTime": 0,
    "cactus": false,
    "type": "Land",
    "name": "Scaredy-shroom",
    "price": 3,
    "health": 1,
    "url": "Resources/scardyshroom.webp"
  }
}